rikabplotlib/_version.py
rikabplotlib/plot_utils.py
rikabplotlib/rikab_column.mplstyle
rikabplotlib/rikab_full.mplstyle
rikabplotlib-0.0.3.dist-info/METADATA
rikabplotlib-0.0.3.dist-info/WHEEL
rikabplotlib-0.0.3.dist-info/licenses/LICENSE
rikabplotlib-0.0.3.dist-info/RECORD
